pyobjtojson/__init__.py
pyobjtojson-0.3.dist-info/LICENSE
pyobjtojson-0.3.dist-info/METADATA
pyobjtojson-0.3.dist-info/WHEEL
pyobjtojson-0.3.dist-info/top_level.txt
pyobjtojson-0.3.dist-info/RECORD
