Metadata-Version: 2.2
Name: pyobjtojson
Version: 0.3
Summary: A Python library that simplifies serializing any Python object to JSON-friendly structures, gracefully handling circular references.
Author-email: "Carlos A. Planchón" <carlosandresplanchonprestes@gmail.com>
License: MIT License
Project-URL: repository, https://github.com/carlosplanchon/pyobjtojson.git
Keywords: json,serialization,circular references,pydantic,dataclasses
Classifier: Intended Audience :: Developers
Classifier: Topic :: Software Development :: Libraries
Classifier: License :: OSI Approved :: MIT License
Classifier: Programming Language :: Python :: 3.13
License-File: LICENSE
